coffeetime/__init__.py
coffeetime-0.0.0.dist-info/WHEEL
coffeetime-0.0.0.dist-info/METADATA
coffeetime-0.0.0.dist-info/RECORD
