Metadata-Version: 2.1
Name: coffeetime
Version: 0.0.0
Summary: Date/time API inspired by JavaScript Temporal
Author: Jeroen Schot
Author-email: jeroenschot@gmail.com
Requires-Python: >=3.6.2
Classifier: Programming Language :: Python :: 3
Classifier: Programming Language :: Python :: 3.10
Classifier: Programming Language :: Python :: 3.7
Classifier: Programming Language :: Python :: 3.8
Classifier: Programming Language :: Python :: 3.9
